clouds/__init__.py
clouds/aws/README.md
clouds/aws/__init__.py
clouds/aws/aws_utils.py
clouds/aws/delete_s3_velero_bucket.py
clouds/aws/roles/README.md
clouds/aws/roles/__init__.py
clouds/aws/roles/roles.py
clouds/aws/session_clients.py
clouds/aws/utilities/delete_aws_resources.py
redhat_qe_cloud_tools-1.0.10.dist-info/LICENSE
redhat_qe_cloud_tools-1.0.10.dist-info/METADATA
redhat_qe_cloud_tools-1.0.10.dist-info/WHEEL
redhat_qe_cloud_tools-1.0.10.dist-info/RECORD
