Metadata-Version: 2.1
Name: redhat-qe-cloud-tools
Version: 1.0.10
Summary: Python utilities to manage cloud services, such as AWS.
Home-page: https://github.com/RedHatQE/cloud-tools
Author: Meni Yakove
Requires-Python: >=3.8,<4.0
Classifier: Programming Language :: Python :: 3
Classifier: Programming Language :: Python :: 3.8
Classifier: Programming Language :: Python :: 3.9
Classifier: Programming Language :: Python :: 3.10
Classifier: Programming Language :: Python :: 3.11
Requires-Dist: boto3 (>=1.28.1,<2.0.0)
Requires-Dist: click (>=8.1.4,<9.0.0)
Requires-Dist: colorlog (>=6.7.0,<7.0.0)
Requires-Dist: configparser (>=6.0.0,<7.0.0)
Requires-Dist: openshift-python-utilities (>=4.14.2,<5.0.0)
Requires-Dist: python-simple-logger (>=1.0.5,<2.0.0)
Project-URL: Repository, https://github.com/RedHatQE/cloud-tools
